knowledge_clustering/__init__.py
knowledge_clustering/_version.py
knowledge_clustering/add_anchor.py
knowledge_clustering/add_quotes.py
knowledge_clustering/autofinder.py
knowledge_clustering/check_update.py
knowledge_clustering/clustering.py
knowledge_clustering/config.py
knowledge_clustering/cst.py
knowledge_clustering/diagnose.py
knowledge_clustering/distance.py
knowledge_clustering/file_updater.py
knowledge_clustering/knowledges.py
knowledge_clustering/misc.py
knowledge_clustering/scope_meaning.py
knowledge_clustering/tex_document.py
knowledge_clustering/data/english.ini
knowledge_clustering/data/french.ini
knowledge_clustering/scripts/__init__.py
knowledge_clustering/scripts/app.py
knowledge_clustering-0.7.4.dist-info/licenses/LICENSE.md
knowledge_clustering-0.7.4.dist-info/METADATA
knowledge_clustering-0.7.4.dist-info/WHEEL
knowledge_clustering-0.7.4.dist-info/entry_points.txt
knowledge_clustering-0.7.4.dist-info/top_level.txt
knowledge_clustering-0.7.4.dist-info/RECORD
