Metadata-Version: 2.4
Name: knowledge-clustering
Version: 0.7.4
Summary: Automated notion clustering for the knowledge LaTeX package
Home-page: https://github.com/remimorvan/knowledge-clustering
Author: Rémi Morvan
Author-email: remi@morvan.xyz
Project-URL: Bug Tracker, https://github.com/remimorvan/knowledge-clustering/issues
Keywords: knowledge :: latex :: clustering
Classifier: Programming Language :: Python :: 3
Classifier: License :: OSI Approved :: MIT License
Classifier: Operating System :: OS Independent
Requires-Python: >=3.9
License-File: LICENSE.md
Requires-Dist: click
Requires-Dist: click_default_group
Requires-Dist: nltk
Requires-Dist: spacy
Requires-Dist: toposort
Requires-Dist: unidecode
Requires-Dist: requests
Provides-Extra: tests
Requires-Dist: pytest; extra == "tests"
Requires-Dist: filecmp; extra == "tests"
Dynamic: license-file
